delismm/.gitignore
delismm/__init__.py
delismm/api/__init__.py
delismm/api/__main__.py
delismm/api/client.py
delismm/control/__init__.py
delismm/control/createDLightModels.py
delismm/control/tank.py
delismm/control/thermalhmm.py
delismm/example.py
delismm/frontend/__init__.py
delismm/frontend/main.py
delismm/model/__init__.py
delismm/model/apimodels.py
delismm/model/customsystemfunction.py
delismm/model/doe.py
delismm/model/metrics.py
delismm/model/radialbasisfunctions.py
delismm/model/samplecalculator.py
delismm/model/samplesetreduction.py
delismm/model/surrogate.py
delismm/service/__init__.py
delismm/service/exception.py
delismm/service/modelplotter.py
delismm/service/screening.py
delismm/service/utilities.py
delismm-1.6.8.dist-info/METADATA
delismm-1.6.8.dist-info/WHEEL
delismm-1.6.8.dist-info/licenses/LICENSE.txt
delismm-1.6.8.dist-info/RECORD
