Metadata-Version: 2.4
Name: delismm
Version: 1.6.8
Summary: kriging-based metamodels: doe, sensitivity, kriging creation, model improvement, optimization, assessment
License: DLR 2025
License-File: LICENSE.txt
Keywords: surrogate,metamodel,kriging,doe,screening
Author: Sebastian Freund
Author-email: sebastian.freund@dlr.de
Requires-Python: >=3.10,<4.0
Classifier: License :: Other/Proprietary License
Classifier: Programming Language :: Python :: 3
Classifier: Programming Language :: Python :: 3.10
Classifier: Programming Language :: Python :: 3.11
Classifier: Programming Language :: Python :: 3.12
Classifier: Programming Language :: Python :: 3.13
Classifier: Programming Language :: Python :: 3.14
Requires-Dist: bokeh
Requires-Dist: fastapi
Requires-Dist: matplotlib
Requires-Dist: numpy (<2)
Requires-Dist: pandas
Requires-Dist: patme
Requires-Dist: pydantic
Requires-Dist: scipy
Requires-Dist: uvicorn
Project-URL: Changelog, https://gitlab.dlr.de/sy-stm/software/delismm/-/blob/master/changelog.md
Project-URL: Documentation, https://sy-stm.pages.gitlab.dlr.de/software/delismm/
Project-URL: Homepage, https://gitlab.dlr.de/fa_sw/delismm
Project-URL: Repository, https://gitlab.dlr.de/fa_sw/delismm
